provae/__init__.py
provae/provae/__init__.py
provae/provae/config.py
provae/provae/decoder.py
provae/provae/encoder.py
provae/provae/provae.py
provae-0.1.0.dist-info/LICENSE
provae-0.1.0.dist-info/METADATA
provae-0.1.0.dist-info/WHEEL
provae-0.1.0.dist-info/RECORD
